{
  "indexes": [
    {
      "collectionGroup": "leaderboards",
      "queryScope": "COLLECTION",
      "fields": [
        {
          "fieldPath": "type",
          "order": "ASCENDING"
        },
        {
          "fieldPath": "totalCalories",
          "order": "DESCENDING"
        }
      ]
    },
    {
      "collectionGroup": "leaderboards",
      "queryScope": "COLLECTION",
      "fields": [
        {
          "fieldPath": "type",
          "order": "ASCENDING"
        },
        {
          "fieldPath": "totalMiles",
          "order": "DESCENDING"
        }
      ]
    },
    {
      "collectionGroup": "leaderboards",
      "queryScope": "COLLECTION",
      "fields": [
        {
          "fieldPath": "type",
          "order": "ASCENDING"
        },
        {
          "fieldPath": "totalSteps",
          "order": "DESCENDING"
        }
      ]
    },
    {
      "collectionGroup": "messages",
      "queryScope": "COLLECTION",
      "fields": [
        {
          "fieldPath": "read",
          "order": "ASCENDING"
        },
        {
          "fieldPath": "receiverId",
          "order": "ASCENDING"
        },
        {
          "fieldPath": "timestamp",
          "order": "DESCENDING"
        }
      ]
    }
  ],
  "fieldOverrides": []
}
